{
  "$schema": "https://railway.app/static/spec.json",
  "build": {
    "builder": "RAILPACK",
    "buildCommand": "npm run install:frontend && npm run build:frontend",
    "watchPatterns": [
      "frontend/src/**",
      "frontend/package.json",
      "package.json"
    ]
  },
  "deploy": {
    "startCommand": "cd frontend && npm run preview",
    "healthcheckPath": "/",
    "restartPolicyType": "ON_FAILURE",
    "restartPolicyMaxRetries": 10,
    "runtime": "v2",
    "resources": {
      "cpu": 2000,
      "memory": 1024
    }
  }
}
